<?xml version="1.0" encoding="UTF-8"?>
<beans xmlns="http://www.springframework.org/schema/beans"
       xmlns:xsi="http://www.w3.org/2001/XMLSchema-instance"
       xmlns:context="http://www.springframework.org/schema/context"
       xmlns:jee="http://www.springframework.org/schema/jee"
       xsi:schemaLocation="http://www.springframework.org/schema/beans http://www.springframework.org/schema/beans/spring-beans-3.0.xsd
						http://www.springframework.org/schema/context http://www.springframework.org/schema/context/spring-context.xsd

                        http://www.springframework.org/schema/jee  http://www.springframework.org/schema/jee/spring-jee-3.2.xsd">

    <context:annotation-config/>
    <import resource="classpath:config.xml"/>

    <context:component-scan
            base-package="eu.europeana.cloud.service.dps.rest"/>

    <bean id="permissionManager"
          class="eu.europeana.cloud.service.dps.utils.PermissionManager"/>

    <bean id="filesCounterFactory" class="eu.europeana.cloud.service.dps.utils.files.counter.FilesCounterFactory"
          scope="prototype"/>

    <bean id="taskSubmitService" class="eu.europeana.cloud.service.dps.service.kafka.TaskKafkaSubmitService">
        <constructor-arg name="kafkaBroker">
            <jee:jndi-lookup expected-type="java.lang.String" jndi-name="java:comp/env/dps/kafka/brokerLocation"/>
        </constructor-arg>
        <constructor-arg name="kafkaGroupId">
            <jee:jndi-lookup expected-type="java.lang.String" jndi-name="java:comp/env/dps/kafka/groupId"/>
        </constructor-arg>
        <constructor-arg name="zookeeperAddress">
            <jee:jndi-lookup expected-type="java.lang.String" jndi-name="java:comp/env/dps/zookeeper/address"/>
        </constructor-arg>
    </bean>

    <bean id="recordSubmitService" class="eu.europeana.cloud.service.dps.service.kafka.RecordKafkaSubmitService">
        <constructor-arg name="kafkaBroker">
            <jee:jndi-lookup expected-type="java.lang.String" jndi-name="java:comp/env/dps/kafka/brokerLocation"/>
        </constructor-arg>
        <constructor-arg name="kafkaGroupId">
            <jee:jndi-lookup expected-type="java.lang.String" jndi-name="java:comp/env/dps/kafka/groupId"/>
        </constructor-arg>
        <constructor-arg name="zookeeperAddress">
            <jee:jndi-lookup expected-type="java.lang.String" jndi-name="java:comp/env/dps/zookeeper/address"/>
        </constructor-arg>
    </bean>

    <bean id="taskReportService" class="eu.europeana.cloud.service.dps.storm.service.cassandra.CassandraReportService">
        <constructor-arg name="hosts">
            <jee:jndi-lookup expected-type="java.lang.String" jndi-name="java:comp/env/dps/cassandra/hosts"/>
        </constructor-arg>
        <constructor-arg name="port">
            <jee:jndi-lookup expected-type="java.lang.Integer" jndi-name="java:comp/env/dps/cassandra/port"/>
        </constructor-arg>
        <constructor-arg name="keyspaceName">
            <jee:jndi-lookup expected-type="java.lang.String" jndi-name="java:comp/env/dps/cassandra/keyspace"/>
        </constructor-arg>
        <constructor-arg name="userName">
            <jee:jndi-lookup expected-type="java.lang.String" jndi-name="java:comp/env/dps/cassandra/user"/>
        </constructor-arg>
        <constructor-arg name="password">
            <jee:jndi-lookup expected-type="java.lang.String" jndi-name="java:comp/env/dps/cassandra/password"/>
        </constructor-arg>
    </bean>

    <bean id="topologyManger" class="eu.europeana.cloud.service.dps.service.utils.TopologyManager">
        <constructor-arg name="nameList">
            <jee:jndi-lookup expected-type="java.lang.String" jndi-name="java:comp/env/dps/topology/nameList"/>
        </constructor-arg>
    </bean>
    <bean id="mcsLocation" class="java.lang.String">
        <constructor-arg type="java.lang.String">
            <jee:jndi-lookup expected-type="java.lang.String" jndi-name="java:comp/env/dps/mcsLocation"/>
        </constructor-arg>
    </bean>
    <bean id="recordServiceClient" class="eu.europeana.cloud.mcs.driver.RecordServiceClient" scope="prototype">
        <constructor-arg name="baseUrl" ref="mcsLocation"/>
    </bean>

    <bean id="fileServiceClient" class="eu.europeana.cloud.mcs.driver.FileServiceClient" scope="prototype">
        <constructor-arg name="baseUrl" ref="mcsLocation"/>
    </bean>

    <bean id="dataSetServiceClient" class="eu.europeana.cloud.mcs.driver.DataSetServiceClient" scope="prototype">
        <constructor-arg name="baseUrl" ref="mcsLocation"/>
    </bean>


    <bean id="dpsCassandraProvider" class="eu.europeana.cloud.cassandra.CassandraConnectionProvider">
        <constructor-arg name="hosts">
            <jee:jndi-lookup expected-type="java.lang.String" jndi-name="java:comp/env/dps/cassandra/hosts"/>
        </constructor-arg>
        <constructor-arg name="port">
            <jee:jndi-lookup expected-type="java.lang.Integer" jndi-name="java:comp/env/dps/cassandra/port"/>
        </constructor-arg>
        <constructor-arg name="keyspaceName">
            <jee:jndi-lookup expected-type="java.lang.String" jndi-name="java:comp/env/dps/cassandra/keyspace"/>
        </constructor-arg>
        <constructor-arg name="userName">
            <jee:jndi-lookup expected-type="java.lang.String" jndi-name="java:comp/env/dps/cassandra/user"/>
        </constructor-arg>
        <constructor-arg name="password">
            <jee:jndi-lookup expected-type="java.lang.String" jndi-name="java:comp/env/dps/cassandra/password"/>
        </constructor-arg>
    </bean>

    <bean id="applicationIdentifier" class="java.lang.String">
        <constructor-arg>
            <jee:jndi-lookup expected-type="java.lang.String" jndi-name="java:comp/env/dps/appId"/>
        </constructor-arg>
    </bean>

    <bean class="org.springframework.beans.factory.config.MethodInvokingFactoryBean">
        <property name="targetClass" value="org.springframework.security.core.context.SecurityContextHolder"/>
        <property name="targetMethod" value="setStrategyName"/>
        <property name="arguments">
            <list>
                <value>MODE_INHERITABLETHREADLOCAL</value>
            </list>
        </property>
    </bean>


    <bean id="taskDAO" class="eu.europeana.cloud.service.dps.storm.utils.CassandraTaskInfoDAO">
        <constructor-arg ref="dpsCassandraProvider"/>
    </bean>

    <bean id="tasksDAO" class="eu.europeana.cloud.service.dps.storm.utils.TasksByStateDAO">
        <constructor-arg ref="dpsCassandraProvider"/>
    </bean>


    <bean id="killService" class="eu.europeana.cloud.service.dps.storm.service.cassandra.CassandraKillService">
        <constructor-arg ref="dpsCassandraProvider"/>
    </bean>

    <bean id="validationStatisticsService"
          class="eu.europeana.cloud.service.dps.storm.service.cassandra.CassandraValidationStatisticsService">
    </bean>
    <bean id="cassandraNodeStatisticsDAO" class="eu.europeana.cloud.service.dps.storm.utils.CassandraNodeStatisticsDAO">
        <constructor-arg ref="dpsCassandraProvider"/>
    </bean>
    <bean id="cassandraAttributeStatisticsDAO"
          class="eu.europeana.cloud.service.dps.storm.utils.CassandraAttributeStatisticsDAO">
        <constructor-arg ref="dpsCassandraProvider"/>
    </bean>


    <import resource="authentication.xml"/>
    <import resource="authorization.xml"/>
</beans>
